tripwires/__init__.py
tripwires/cli.py
tripwires/core.py
tripwires/exceptions.py
tripwires/file_types.py
tripwires/manifest.py
tripwires/model.py
tripwires/output/__init__.py
tripwires/output/base.py
tripwires/output/console.py
tripwires-0.1.1.dist-info/METADATA
tripwires-0.1.1.dist-info/WHEEL
tripwires-0.1.1.dist-info/entry_points.txt
tripwires-0.1.1.dist-info/licenses/LICENSE
tripwires-0.1.1.dist-info/RECORD
