Metadata-Version: 2.4
Name: tripwires
Version: 0.1.1
Summary: Lightweight guardrails for AI-assisted development teams
License-File: LICENSE
Keywords: development,guardrails,hash,monitoring,ci,testing
Author: tripwires contributors
Requires-Python: >=3.10,<4.0
Classifier: Development Status :: 4 - Beta
Classifier: Environment :: Console
Classifier: Intended Audience :: Developers
Classifier: License :: OSI Approved :: Apache Software License
Classifier: Operating System :: OS Independent
Classifier: Programming Language :: Python :: 3
Classifier: Programming Language :: Python :: 3.10
Classifier: Programming Language :: Python :: 3.11
Classifier: Programming Language :: Python :: 3.12
Classifier: Programming Language :: Python :: 3.13
Classifier: Programming Language :: Python :: 3.14
Classifier: Topic :: Software Development :: Quality Assurance
Classifier: Topic :: Software Development :: Testing
Classifier: Topic :: Utilities
Requires-Dist: pyyaml (>=6.0,<7.0)
Requires-Dist: typer (>=0.20.0,<0.21.0)
Requires-Dist: xxhash (>=3.6.0,<4.0.0)
Project-URL: Documentation, https://github.com/mikeAdamss/tripwires#readme
Project-URL: Homepage, https://github.com/mikeAdamss/tripwires
Project-URL: Repository, https://github.com/mikeAdamss/tripwires
